{
  "agent": {
    "rew_mean": 0.0,
    "rew_std": 0.0,
    "rew_best": 0.0,
    "rew_best_count": 50,
    "rew_worst": 0.0,
    "tardiness_mean": 0.0,
    "tardiness_std": 0.0,
    "tardiness_max_mean": 0.0,
    "makespan_tests": [
      20920,
      553948,
      15660,
      112200,
      20340,
      26424,
      219500,
      49800,
      3589000,
      84320,
      14265,
      323460,
      660700,
      42320,
      190798,
      689100,
      4736440,
      5940000,
      515480,
      2270200,
      796800,
      1221750,
      74676,
      314880,
      846400,
      834600,
      855900,
      1080660,
      516200,
      727920,
      2392000,
      772600,
      56355,
      65360,
      608800,
      100380,
      498100,
      147940,
      498940,
      669500,
      241492,
      3530300,
      24600,
      17480,
      4485860,
      16992,
      112500,
      41724,
      16660,
      177800
    ],
    "makespan_mean": 836400.88,
    "rew_worst_quantile_border": 0.0,
    "rew_cvar": 0.0,
    "rew_perc_good_solutions": 1.0,
    "num_tests": 50
  },
  "test-data-file-names": [
    "bom_wide_2_7_20_5_No1",
    "bom_wide_5_9_15_5_No1",
    "bom_wide_2_7_20_10_No1",
    "bom_wide_2_10_30_15_No2",
    "bom_wide_2_11_13_5_No2",
    "bom_wide_2_9_10_5_No1",
    "bom_wide_2_10_10_5_No2",
    "bom_wide_4_6_16_4_No1",
    "bom_wide_5_10_10_5_No1",
    "bom_wide_3_7_10_5_No1",
    "bom_wide_3_5_16_4_No1",
    "bom_wide_5_6_20_4_No2",
    "bom_wide_3_10_30_15_No2",
    "bom_wide_3_7_15_5_No1",
    "bom_wide_3_8_15_5_No2",
    "bom_wide_3_10_10_5_No2",
    "bom_wide_5_3_10_5_No1",
    "bom_wide_4_8_10_5_No2",
    "bom_wide_5_8_20_5_No2",
    "bom_wide_5_10_30_15_No2",
    "bom_wide_4_10_10_5_No1",
    "bom_wide_5_4_16_4_No2",
    "bom_wide_3_9_15_5_No1",
    "bom_wide_4_7_12_5_No1",
    "bom_wide_4_6_40_15_No1",
    "bom_wide_4_10_30_15_No2",
    "bom_wide_4_10_30_15_No1",
    "bom_wide_4_7_12_5_No2",
    "bom_wide_4_6_40_15_No2",
    "bom_wide_5_8_20_5_No1",
    "bom_wide_5_10_30_15_No1",
    "bom_wide_4_10_10_5_No2",
    "bom_wide_5_4_16_4_No1",
    "bom_wide_3_9_15_5_No2",
    "bom_wide_3_10_10_5_No1",
    "bom_wide_3_8_15_5_No1",
    "bom_wide_5_3_10_5_No2",
    "bom_wide_4_8_10_5_No1",
    "bom_wide_5_6_20_4_No1",
    "bom_wide_3_10_30_15_No1",
    "bom_wide_4_6_16_4_No2",
    "bom_wide_5_10_10_5_No2",
    "bom_wide_3_5_16_4_No2",
    "bom_wide_2_7_20_5_No2",
    "bom_wide_5_9_15_5_No2",
    "bom_wide_2_7_20_10_No2",
    "bom_wide_2_10_30_15_No1",
    "bom_wide_2_11_13_5_No1",
    "bom_wide_2_9_10_5_No2",
    "bom_wide_2_10_10_5_No1"
  ]
}