{
  "agent": {
    "rew_mean": 0.0,
    "rew_std": 0.0,
    "rew_best": 0.0,
    "rew_best_count": 275,
    "rew_worst": 0.0,
    "tardiness_mean": 0.0,
    "tardiness_std": 0.0,
    "tardiness_max_mean": 0.0,
    "makespan_tests": [
      36602,
      356700,
      105700,
      15190,
      69640,
      76278,
      61262,
      157681,
      21332,
      152828,
      53105,
      36964,
      57254,
      40076,
      54346,
      161543,
      22390,
      119622,
      93605,
      34607,
      74322,
      128234,
      664075,
      97670,
      39891,
      98354,
      336395,
      199246,
      343938,
      31529,
      48184,
      174198,
      1123276,
      28302,
      15505,
      700744,
      63687,
      103556,
      63786,
      106408,
      28884,
      23392,
      104031,
      18707,
      32784,
      87570,
      21107,
      74649,
      74178,
      35910,
      763833,
      68712,
      55448,
      135421,
      49578,
      54922,
      56052,
      72259,
      51516,
      115911,
      115907,
      40868,
      122731,
      66195,
      92282,
      20142,
      53133,
      79042,
      207228,
      24536,
      442760,
      158513,
      174835,
      54295,
      96437,
      98795,
      43815,
      41048,
      57306,
      452869,
      431652,
      126820,
      80666,
      57413,
      100937,
      16971,
      135277,
      111102,
      110996,
      101577,
      51250,
      588267,
      52221,
      79642,
      82396,
      57228,
      275665,
      816319,
      56579,
      41354,
      79489,
      16564,
      30996,
      56875,
      44838,
      49376,
      100448,
      126325,
      51581,
      98795,
      30656,
      129549,
      463051,
      31896,
      98381,
      64878,
      300630,
      98993,
      33247,
      102020,
      39900,
      45139,
      33675,
      598270,
      15830,
      88133,
      49666,
      446506,
      18992,
      26075,
      75170,
      122652,
      34961,
      68033,
      27594,
      93943,
      47120,
      102999,
      125062,
      30141,
      99825,
      220296,
      47134,
      45177,
      68923,
      142621,
      15480,
      119289,
      964281,
      53210,
      61443,
      244504,
      40537,
      32204,
      118531,
      628031,
      31824,
      165555,
      129251,
      59827,
      87938,
      56968,
      18778,
      21916,
      310966,
      347116,
      35311,
      42327,
      126729,
      54532,
      83079,
      33437,
      26336,
      106184,
      57780,
      47443,
      40700,
      136822,
      61861,
      16972,
      99093,
      646449,
      300372,
      105631,
      50184,
      34325,
      191013,
      121277,
      123535,
      265759,
      145111,
      84778,
      80361,
      147079,
      105608,
      91896,
      79089,
      122483,
      34464,
      129129,
      121162,
      328454,
      158777,
      31900,
      48760,
      48467,
      99016,
      32204,
      61987,
      129916,
      61716,
      78769,
      98993,
      72383,
      211132,
      48489,
      480960,
      39853,
      112913,
      35154,
      71276,
      620181,
      56461,
      77061,
      922528,
      309490,
      94776,
      98795,
      28772,
      67865,
      45033,
      36040,
      48811,
      27367,
      79840,
      257562,
      194658,
      15298,
      205703,
      49625,
      176475,
      36058,
      47586,
      121237,
      65868,
      122483,
      20142,
      116945,
      46589,
      41340,
      18108,
      515789,
      41048,
      49144,
      24257,
      75569,
      100704,
      61971,
      98795,
      57630,
      40909,
      26299,
      49862,
      40552,
      61674,
      52522,
      65553,
      12936,
      33075,
      49356,
      28315,
      43436,
      72245,
      113551,
      82663
    ],
    "makespan_mean": 124312.77818181818,
    "rew_worst_quantile_border": 0.0,
    "rew_cvar": 0.0,
    "rew_perc_good_solutions": 1.0,
    "num_tests": 275
  },
  "test-data-file-names": [
    "bom_tubes_p50_ao15_am18_4_m25_ao15_am16_2",
    "bom_tubes_p50_ao15_am18_3",
    "bom_tubes_p50_ao15_am18_3_m25_ao15_am17_3",
    "bom_tubes_p20_ao12_am18_1_m30_ao12_am19_2",
    "bom_tubes_p10_ao11_am18_2_m25_ao11_am23_4",
    "bom_tubes_p30_ao13_am18_5_m30_ao13_am18_5",
    "bom_tubes_p10_ao11_am18_4_m25_ao11_am22_3",
    "bom_tubes_p30_ao13_am18_1_m30_ao13_am16_2",
    "bom_tubes_p30_ao13_am18_2",
    "bom_tubes_p50_ao15_am18_1_m25_ao15_am20_2",
    "bom_tubes_p10_ao11_am18_4_m10_ao11_am9_1",
    "bom_tubes_p20_ao12_am18_5_m13_ao12_am12_2",
    "bom_tubes_p20_ao12_am18_5_m30_ao12_am20_1",
    "bom_tubes_p20_ao12_am18_3_m13_ao12_am12_1",
    "bom_tubes_p10_ao11_am18_5_m10_ao11_am9_1",
    "bom_tubes_p30_ao13_am18_4_m30_ao13_am16_2",
    "bom_tubes_p20_ao12_am18_5_m30_ao12_am19_4",
    "bom_tubes_p10_ao11_am18_3_m25_ao11_am21_3",
    "bom_tubes_p10_ao11_am18_3_m25_ao11_am19_2",
    "bom_tubes_p20_ao12_am18_5_m30_ao12_am21_5",
    "bom_tubes_p20_ao12_am18_3_m13_ao12_am13_5",
    "bom_tubes_p30_ao13_am18_5_m10_ao13_am10_4",
    "bom_tubes_p50_ao15_am18_5_m10_ao15_am9_1",
    "bom_tubes_p40_ao14_am18_1_m12_ao14_am12_4",
    "bom_tubes_p50_ao15_am18_1_m10_ao15_am10_4",
    "bom_tubes_p40_ao14_am18_2_m12_ao14_am11_2",
    "bom_tubes_p40_ao14_am18_5_m35_ao14_am27_2",
    "bom_tubes_p40_ao14_am18_4_m12_ao14_am12_4",
    "bom_tubes_p50_ao15_am18_5_m10_ao15_am10_2",
    "bom_tubes_p40_ao14_am18_3_m35_ao14_am24_4",
    "bom_tubes_p30_ao13_am18_1_m10_ao13_am10_2",
    "bom_tubes_p50_ao15_am18_4_m10_ao15_am10_4",
    "bom_tubes_p40_ao14_am18_5_m12_ao14_am12_2",
    "bom_tubes_p10_ao11_am18_4_m10_ao11_am10_4",
    "bom_tubes_p40_ao14_am18_2_m35_ao14_am24_2",
    "bom_tubes_p40_ao14_am18_5_m12_ao14_am12_3",
    "bom_tubes_p10_ao11_am18_4_m10_ao11_am10_5",
    "bom_tubes_p40_ao14_am18_1_m35_ao14_am26_1",
    "bom_tubes_p50_ao15_am18_2_m10_ao15_am9_1",
    "bom_tubes_p30_ao13_am18_1_m10_ao13_am10_3",
    "bom_tubes_p40_ao14_am18_2_m35_ao14_am28_3",
    "bom_tubes_p40_ao14_am18_4_m12_ao14_am12_5",
    "bom_tubes_p50_ao15_am18_5_m10_ao15_am10_3",
    "bom_tubes_p10_ao11_am18_5_m10_ao11_am10_3",
    "bom_tubes_p10_ao11_am18_1_m10_ao11_am10_5",
    "bom_tubes_p30_ao13_am18_5_m30_ao13_am22_4",
    "bom_tubes_p20_ao12_am18_3_m13_ao12_am13_4",
    "bom_tubes_p30_ao13_am18_5_m30_ao13_am17_1",
    "bom_tubes_p30_ao13_am18_4_m30_ao13_am16_3",
    "bom_tubes_p50_ao15_am18_1_m25_ao15_am16_3",
    "bom_tubes_p20_ao12_am18_4_m13_ao12_am13_1",
    "bom_tubes_p10_ao11_am18_3_m10_ao11_am9_1",
    "bom_tubes_p20_ao12_am18_3_m30_ao12_am20_3",
    "bom_tubes_p30_ao13_am18_3",
    "bom_tubes_p30_ao13_am18_2_m30_ao13_am19_5",
    "bom_tubes_p10_ao11_am18_2_m10_ao11_am9_1",
    "bom_tubes_p10_ao11_am18_5_m25_ao11_am22_4",
    "bom_tubes_p50_ao15_am18_3_m25_ao15_am17_2",
    "bom_tubes_p50_ao15_am18_2",
    "bom_tubes_p30_ao13_am18_5_m10_ao13_am10_2",
    "bom_tubes_p40_ao14_am18_1_m35_ao14_am25_3",
    "bom_tubes_p40_ao14_am18_1_m12_ao14_am12_2",
    "bom_tubes_p10_ao11_am18_1_m10_ao11_am10_2",
    "bom_tubes_p30_ao13_am18_4_m10_ao13_am10_4",
    "bom_tubes_p50_ao15_am18_5_m10_ao15_am10_4",
    "bom_tubes_p10_ao11_am18_5_m10_ao11_am10_4",
    "bom_tubes_p40_ao14_am18_3_m35_ao14_am24_2",
    "bom_tubes_p40_ao14_am18_2_m12_ao14_am12_1",
    "bom_tubes_p40_ao14_am18_5_m35_ao14_am24_1",
    "bom_tubes_p30_ao13_am18_1_m10_ao13_am10_4",
    "bom_tubes_p40_ao14_am18_5_m12_ao14_am12_4",
    "bom_tubes_p20_ao12_am18_4_m30_ao12_am23_4",
    "bom_tubes_p50_ao15_am18_5",
    "bom_tubes_p10_ao11_am18_4_m10_ao11_am8_3",
    "bom_tubes_p10_ao11_am18_3_m25_ao11_am23_4",
    "bom_tubes_p40_ao14_am18_1",
    "bom_tubes_p30_ao13_am18_5_m30_ao13_am20_2",
    "bom_tubes_p30_ao13_am18_4",
    "bom_tubes_p10_ao11_am18_2_m10_ao11_am8_2",
    "bom_tubes_p20_ao12_am18_2_m13_ao12_am13_5",
    "bom_tubes_p20_ao12_am18_4_m30_ao12_am21_5",
    "bom_tubes_p30_ao13_am18_5_m10_ao13_am9_1",
    "bom_tubes_p10_ao11_am18_2_m25_ao11_am21_3",
    "bom_tubes_p20_ao12_am18_1_m30_ao12_am23_4",
    "bom_tubes_p10_ao11_am18_4_m25_ao11_am20_4",
    "bom_tubes_p20_ao12_am18_5_m30_ao12_am21_3",
    "bom_tubes_p20_ao12_am18_4_m13_ao12_am12_2",
    "bom_tubes_p50_ao15_am18_1_m25_ao15_am17_1",
    "bom_tubes_p20_ao12_am18_1_m30_ao12_am22_1",
    "bom_tubes_p30_ao13_am18_3_m10_ao13_am9_1",
    "bom_tubes_p10_ao11_am18_1_m25_ao11_am22_4",
    "bom_tubes_p20_ao12_am18_4_m13_ao12_am12_3",
    "bom_tubes_p10_ao11_am18_3_m10_ao11_am8_3",
    "bom_tubes_p30_ao13_am18_1_m30_ao13_am20_5",
    "bom_tubes_p50_ao15_am18_4_m25_ao15_am14_4",
    "bom_tubes_p30_ao13_am18_1_m30_ao13_am18_4",
    "bom_tubes_p50_ao15_am18_3_m25_ao15_am15_5",
    "bom_tubes_p20_ao12_am18_2_m13_ao12_am13_4",
    "bom_tubes_p30_ao13_am18_3_m30_ao13_am18_1",
    "bom_tubes_p50_ao15_am18_5_m25_ao15_am16_3",
    "bom_tubes_p10_ao11_am18_2_m25_ao11_am17_2",
    "bom_tubes_p20_ao12_am18_3_m13_ao12_am11_3",
    "bom_tubes_p50_ao15_am18_2_m25_ao15_am17_2",
    "bom_tubes_p30_ao13_am18_5",
    "bom_tubes_p30_ao13_am18_2_m10_ao13_am9_1",
    "bom_tubes_p50_ao15_am18_1_m25_ao15_am18_4",
    "bom_tubes_p20_ao12_am18_4_m30_ao12_am22_1",
    "bom_tubes_p50_ao15_am18_4_m25_ao15_am17_1",
    "bom_tubes_p30_ao13_am18_3_m30_ao13_am19_5",
    "bom_tubes_p20_ao12_am18_1",
    "bom_tubes_p20_ao12_am18_3_m30_ao12_am22_4",
    "bom_tubes_p20_ao12_am18_1_m30_ao12_am19_5",
    "bom_tubes_p50_ao15_am18_3_m25_ao15_am17_4",
    "bom_tubes_p30_ao13_am18_4_m30_ao13_am20_5",
    "bom_tubes_p50_ao15_am18_4",
    "bom_tubes_p50_ao15_am18_4_m10_ao15_am10_3",
    "bom_tubes_p40_ao14_am18_5_m12_ao14_am12_5",
    "bom_tubes_p10_ao11_am18_1",
    "bom_tubes_p40_ao14_am18_2_m35_ao14_am29_1",
    "bom_tubes_p30_ao13_am18_1_m10_ao13_am8_5",
    "bom_tubes_p10_ao11_am18_1_m10_ao11_am8_3",
    "bom_tubes_p40_ao14_am18_2_m35_ao14_am28_5",
    "bom_tubes_p40_ao14_am18_4_m12_ao14_am12_3",
    "bom_tubes_p50_ao15_am18_5_m10_ao15_am10_5",
    "bom_tubes_p10_ao11_am18_5_m10_ao11_am10_5",
    "bom_tubes_p40_ao14_am18_3_m35_ao14_am24_3",
    "bom_tubes_p30_ao13_am18_4_m10_ao13_am10_5",
    "bom_tubes_p40_ao14_am18_5_m35_ao14_am27_5",
    "bom_tubes_p40_ao14_am18_2_m35_ao14_am26_4",
    "bom_tubes_p50_ao15_am18_1_m10_ao15_am10_3",
    "bom_tubes_p40_ao14_am18_1_m12_ao14_am12_3",
    "bom_tubes_p40_ao14_am18_1_m12_ao14_am11_5",
    "bom_tubes_p10_ao11_am18_1_m10_ao11_am9_4",
    "bom_tubes_p10_ao11_am18_2",
    "bom_tubes_p50_ao15_am18_2_m10_ao15_am9_4",
    "bom_tubes_p50_ao15_am18_4_m10_ao15_am8_1",
    "bom_tubes_p40_ao14_am18_4_m35_ao14_am24_5",
    "bom_tubes_p40_ao14_am18_3_m12_ao14_am12_5",
    "bom_tubes_p50_ao15_am18_4_m10_ao15_am9_5",
    "bom_tubes_p10_ao11_am18_3_m10_ao11_am10_5",
    "bom_tubes_p40_ao14_am18_2_m12_ao14_am12_3",
    "bom_tubes_p50_ao15_am18_3_m10_ao15_am10_5",
    "bom_tubes_p30_ao13_am18_2_m10_ao13_am10_5",
    "bom_tubes_p40_ao14_am18_4_m35_ao14_am26_4",
    "bom_tubes_p40_ao14_am18_3_m35_ao14_am26_1",
    "bom_tubes_p50_ao15_am18_4_m25_ao15_am15_3",
    "bom_tubes_p30_ao13_am18_1_m30_ao13_am19_3",
    "bom_tubes_p50_ao15_am18_2_m25_ao15_am18_4",
    "bom_tubes_p20_ao12_am18_4_m30_ao12_am20_3",
    "bom_tubes_p50_ao15_am18_5_m25_ao15_am19_5",
    "bom_tubes_p20_ao12_am18_3_m30_ao12_am21_2",
    "bom_tubes_p20_ao12_am18_2_m13_ao12_am12_3",
    "bom_tubes_p10_ao11_am18_5_m25_ao11_am19_5",
    "bom_tubes_p10_ao11_am18_2_m25_ao11_am21_1",
    "bom_tubes_p30_ao13_am18_5_m10_ao13_am9_3",
    "bom_tubes_p20_ao12_am18_4_m13_ao12_am13_4",
    "bom_tubes_p30_ao13_am18_2_m30_ao13_am22_4",
    "bom_tubes_p20_ao12_am18_1_m13_ao12_am11_5",
    "bom_tubes_p10_ao11_am18_3_m10_ao11_am9_4",
    "bom_tubes_p30_ao13_am18_3_m30_ao13_am18_2",
    "bom_tubes_p20_ao12_am18_1_m30_ao12_am20_3",
    "bom_tubes_p50_ao15_am18_2_m25_ao15_am17_1",
    "bom_tubes_p20_ao12_am18_5_m13_ao12_am11_3",
    "bom_tubes_p40_ao14_am18_3",
    "bom_tubes_p50_ao15_am18_5_m25_ao15_am17_4",
    "bom_tubes_p20_ao12_am18_4_m13_ao12_am11_5",
    "bom_tubes_p10_ao11_am18_5_m25_ao11_am22_1",
    "bom_tubes_p50_ao15_am18_2_m25_ao15_am16_5",
    "bom_tubes_p20_ao12_am18_2",
    "bom_tubes_p20_ao12_am18_1_m13_ao12_am13_4",
    "bom_tubes_p30_ao13_am18_4_m10_ao13_am9_3",
    "bom_tubes_p10_ao11_am18_1_m25_ao11_am19_2",
    "bom_tubes_p50_ao15_am18_2_m25_ao15_am12_3",
    "bom_tubes_p30_ao13_am18_3_m30_ao13_am14_3",
    "bom_tubes_p30_ao13_am18_4_m10_ao13_am9_2",
    "bom_tubes_p30_ao13_am18_2_m30_ao13_am15_1",
    "bom_tubes_p20_ao12_am18_3",
    "bom_tubes_p10_ao11_am18_1_m25_ao11_am21_3",
    "bom_tubes_p50_ao15_am18_1_m10_ao15_am9_5",
    "bom_tubes_p40_ao14_am18_2",
    "bom_tubes_p20_ao12_am18_1_m13_ao12_am12_1",
    "bom_tubes_p50_ao15_am18_5_m25_ao15_am16_1",
    "bom_tubes_p20_ao12_am18_2_m30_ao12_am19_4",
    "bom_tubes_p20_ao12_am18_2_m30_ao12_am21_5",
    "bom_tubes_p10_ao11_am18_4_m25_ao11_am19_2",
    "bom_tubes_p10_ao11_am18_3_m25_ao11_am24_5",
    "bom_tubes_p20_ao12_am18_2_m13_ao12_am12_2",
    "bom_tubes_p20_ao12_am18_4_m30_ao12_am20_2",
    "bom_tubes_p30_ao13_am18_3_m10_ao13_am9_3",
    "bom_tubes_p20_ao12_am18_2_m30_ao12_am20_1",
    "bom_tubes_p40_ao14_am18_1_m35_ao14_am28_4",
    "bom_tubes_p40_ao14_am18_4_m35_ao14_am27_1",
    "bom_tubes_p40_ao14_am18_3_m12_ao14_am11_1",
    "bom_tubes_p50_ao15_am18_3_m10_ao15_am8_1",
    "bom_tubes_p30_ao13_am18_3_m10_ao13_am10_2",
    "bom_tubes_p40_ao14_am18_1_m12_ao14_am12_1",
    "bom_tubes_p40_ao14_am18_5_m35_ao14_am26_3",
    "bom_tubes_p50_ao15_am18_1_m10_ao15_am10_1",
    "bom_tubes_p30_ao13_am18_2_m10_ao13_am10_4",
    "bom_tubes_p40_ao14_am18_4_m12_ao14_am12_1",
    "bom_tubes_p10_ao11_am18_1_m10_ao11_am8_1",
    "bom_tubes_p50_ao15_am18_3_m10_ao15_am10_4",
    "bom_tubes_p50_ao15_am18_2_m10_ao15_am10_2",
    "bom_tubes_p40_ao14_am18_3_m12_ao14_am12_4",
    "bom_tubes_p10_ao11_am18_3",
    "bom_tubes_p30_ao13_am18_3_m10_ao13_am9_4",
    "bom_tubes_p10_ao11_am18_1_m25_ao11_am22_1",
    "bom_tubes_p10_ao11_am18_3_m25_ao11_am21_1",
    "bom_tubes_p20_ao12_am18_5_m13_ao12_am13_4",
    "bom_tubes_p50_ao15_am18_4_m25_ao15_am15_5",
    "bom_tubes_p20_ao12_am18_2_m30_ao12_am21_2",
    "bom_tubes_p30_ao13_am18_5_m10_ao13_am9_5",
    "bom_tubes_p30_ao13_am18_1_m30_ao13_am18_1",
    "bom_tubes_p20_ao12_am18_2_m30_ao12_am19_3",
    "bom_tubes_p10_ao11_am18_3_m10_ao11_am9_2",
    "bom_tubes_p20_ao12_am18_1_m13_ao12_am11_3",
    "bom_tubes_p20_ao12_am18_2_m13_ao12_am13_1",
    "bom_tubes_p10_ao11_am18_5_m25_ao11_am23_3",
    "bom_tubes_p30_ao13_am18_4_m10_ao13_am8_1",
    "bom_tubes_p10_ao11_am18_4_m25_ao11_am22_1",
    "bom_tubes_p20_ao12_am18_5_m13_ao12_am11_5",
    "bom_tubes_p40_ao14_am18_5",
    "bom_tubes_p50_ao15_am18_5_m25_ao15_am17_2",
    "bom_tubes_p50_ao15_am18_1_m10_ao15_am9_2",
    "bom_tubes_p20_ao12_am18_4",
    "bom_tubes_p50_ao15_am18_3_m25_ao15_am17_1",
    "bom_tubes_p20_ao12_am18_1_m13_ao12_am13_2",
    "bom_tubes_p50_ao15_am18_1",
    "bom_tubes_p10_ao11_am18_4",
    "bom_tubes_p40_ao14_am18_3_m35_ao14_am21_5",
    "bom_tubes_p10_ao11_am18_2_m10_ao11_am10_5",
    "bom_tubes_p40_ao14_am18_1_m35_ao14_am22_5",
    "bom_tubes_p50_ao15_am18_2_m10_ao15_am10_5",
    "bom_tubes_p40_ao14_am18_3_m12_ao14_am12_3",
    "bom_tubes_p40_ao14_am18_2_m12_ao14_am12_5",
    "bom_tubes_p50_ao15_am18_3_m10_ao15_am10_3",
    "bom_tubes_p50_ao15_am18_3_m10_ao15_am9_2",
    "bom_tubes_p30_ao13_am18_2_m10_ao13_am10_3",
    "bom_tubes_p40_ao14_am18_5_m35_ao14_am26_4",
    "bom_tubes_p40_ao14_am18_4_m35_ao14_am26_3",
    "bom_tubes_p40_ao14_am18_4_m12_ao14_am11_2",
    "bom_tubes_p30_ao13_am18_2_m10_ao13_am10_2",
    "bom_tubes_p40_ao14_am18_1_m35_ao14_am24_2",
    "bom_tubes_p50_ao15_am18_4_m10_ao15_am9_2",
    "bom_tubes_p40_ao14_am18_2_m12_ao14_am12_4",
    "bom_tubes_p30_ao13_am18_1_m10_ao13_am10_1",
    "bom_tubes_p10_ao11_am18_2_m10_ao11_am10_4",
    "bom_tubes_p40_ao14_am18_4_m35_ao14_am24_2",
    "bom_tubes_p40_ao14_am18_3_m12_ao14_am12_2",
    "bom_tubes_p50_ao15_am18_2_m10_ao15_am9_3",
    "bom_tubes_p10_ao11_am18_5",
    "bom_tubes_p40_ao14_am18_5_m12_ao14_am12_1",
    "bom_tubes_p20_ao12_am18_5",
    "bom_tubes_p30_ao13_am18_2_m30_ao13_am20_2",
    "bom_tubes_p10_ao11_am18_2_m10_ao11_am9_3",
    "bom_tubes_p10_ao11_am18_1_m25_ao11_am21_5",
    "bom_tubes_p30_ao13_am18_3_m30_ao13_am20_4",
    "bom_tubes_p40_ao14_am18_4",
    "bom_tubes_p30_ao13_am18_1",
    "bom_tubes_p30_ao13_am18_4_m30_ao13_am19_4",
    "bom_tubes_p10_ao11_am18_4_m10_ao11_am9_2",
    "bom_tubes_p10_ao11_am18_4_m25_ao11_am21_5",
    "bom_tubes_p20_ao12_am18_3_m30_ao12_am20_1",
    "bom_tubes_p20_ao12_am18_5_m13_ao12_am12_1",
    "bom_tubes_p30_ao13_am18_2_m30_ao13_am22_3",
    "bom_tubes_p20_ao12_am18_5_m30_ao12_am20_2",
    "bom_tubes_p20_ao12_am18_3_m13_ao12_am12_2",
    "bom_tubes_p20_ao12_am18_3_m30_ao12_am21_5",
    "bom_tubes_p10_ao11_am18_5_m10_ao11_am9_2",
    "bom_tubes_p10_ao11_am18_5_m25_ao11_am19_2",
    "bom_tubes_p10_ao11_am18_2_m25_ao11_am24_5",
    "bom_tubes_p30_ao13_am18_4_m30_ao13_am16_1",
    "bom_tubes_p30_ao13_am18_5_m30_ao13_am17_3",
    "bom_tubes_p30_ao13_am18_3_m10_ao13_am9_5",
    "bom_tubes_p50_ao15_am18_1_m25_ao15_am17_5"
  ]
}